folklore_config/__init__.py
folklore_config/_config.py
folklore_config/_settings.py
folklore_config/utils.py
folklore_config-0.2.0.dist-info/LICENSE
folklore_config-0.2.0.dist-info/METADATA
folklore_config-0.2.0.dist-info/WHEEL
folklore_config-0.2.0.dist-info/top_level.txt
folklore_config-0.2.0.dist-info/RECORD
