Metadata-Version: 2.1
Name: folklore-config
Version: 0.2.0
Summary: The Folklore service framework configuration module
Home-page: https://github.com/maralla/folklore-config
Author: maralla
Author-email: maralla.ai@gmail.com
License: UNKNOWN
Platform: UNKNOWN
Requires-Dist: PyYAML
